<?xml version="1.0"?>
<PropertyList>
  <flightplan>
    <wpt>
      <name>WPT1</name>
      <lat>13.183183</lat>
      <lon>77.600419</lon>
      <alt>5000.000000</alt>
      <ktas>388.768898</ktas>
      <on-ground>0</on-ground>
      <gear-down>0</gear-down>
      <flaps-down>0</flaps-down>
    </wpt>

    <wpt>
      <name>WPT112</name>
      <lat>13.379791</lat>
      <lon>77.636087</lon>
      <alt>5000.000000</alt>
      <ktas>388.768898</ktas>
      <on-ground>0</on-ground>
      <gear-down>0</gear-down>
      <flaps-down>0</flaps-down>
    </wpt>


    <wpt>
      <name>WPT232</name>
      <lat>13.592335</lat>
      <lon>77.674713</lon>
      <alt>5000.000000</alt>
      <ktas>388.768898</ktas>
      <on-ground>0</on-ground>
      <gear-down>0</gear-down>
      <flaps-down>0</flaps-down>
    </wpt>


    <wpt>
      <name>WPT294</name>
      <lat>13.702147</lat>
      <lon>77.694697</lon>
      <alt>5000.000000</alt>
      <ktas>388.768898</ktas>
      <on-ground>0</on-ground>
      <gear-down>0</gear-down>
      <flaps-down>0</flaps-down>
    </wpt>


    <wpt>
      <name>WPT357</name>
      <lat>13.813729</lat>
      <lon>77.715022</lon>
      <alt>5000.000000</alt>
      <ktas>388.768898</ktas>
      <on-ground>0</on-ground>
      <gear-down>0</gear-down>
      <flaps-down>0</flaps-down>
    </wpt>

    <wpt>
      <name>WPT440</name>
      <lat>13.960730</lat>
      <lon>77.741829</lon>
      <alt>5000.000000</alt>
      <ktas>388.768898</ktas>
      <on-ground>0</on-ground>
      <gear-down>0</gear-down>
      <flaps-down>0</flaps-down>
    </wpt>


    <wpt>
      <name>WPT516</name>
      <lat>14.095332</lat>
      <lon>77.766406</lon>
      <alt>5000.000000</alt>
      <ktas>388.768898</ktas>
      <on-ground>0</on-ground>
      <gear-down>0</gear-down>
      <flaps-down>0</flaps-down>
    </wpt>


    <wpt>
      <name>END</name>
      <lat>14.244099</lat>
      <lon>77.793603</lon>
      <alt>5000.000000</alt>
      <ktas>388.768898</ktas>
      <on-ground>0</on-ground>
      <gear-down>0</gear-down>
      <flaps-down>0</flaps-down>
    </wpt>

    <wpt>
      <name>EOF</name>
    </wpt>

  </flightplan>
</PropertyList>